projectkiwi/__init__.py
projectkiwi/connector.py
projectkiwi/data.py
projectkiwi/ml.py
projectkiwi/models.py
projectkiwi/tools.py
projectkiwi/transforms.py
projectkiwi-0.6.0.dist-info/LICENSE
projectkiwi-0.6.0.dist-info/METADATA
projectkiwi-0.6.0.dist-info/WHEEL
projectkiwi-0.6.0.dist-info/top_level.txt
projectkiwi-0.6.0.dist-info/RECORD
