Metadata-Version: 2.1
Name: projectkiwi
Version: 0.6.0
Summary: Python tools for projectkiwi.io
Home-page: https://github.com/michaelthoreau/projectkiwi
Author: Michael Thoreau
Author-email: michael@projectkiwi.io
License: MIT
Keywords: GIS,ML,OTHERBUZZWORDS
Platform: UNKNOWN
Classifier: Programming Language :: Python :: 3
Classifier: License :: OSI Approved :: MIT License
Classifier: Operating System :: OS Independent
Requires-Python: >=3.3
License-File: LICENSE
Requires-Dist: numpy
Requires-Dist: pillow
Requires-Dist: pydantic
Requires-Dist: requests
Requires-Dist: shapely
Requires-Dist: torch
Requires-Dist: torchvision
Requires-Dist: scikit-image
